customaiagent/__init__.py
customaiagent/core/deployer.py
customaiagent-0.1.2.dist-info/METADATA
customaiagent-0.1.2.dist-info/WHEEL
customaiagent-0.1.2.dist-info/RECORD
